README
setup.py
MetaPathways_Python.egg-info/PKG-INFO
MetaPathways_Python.egg-info/SOURCES.txt
MetaPathways_Python.egg-info/dependency_links.txt
MetaPathways_Python.egg-info/top_level.txt
metapathways2/MetaPathways.py
metapathways2/__init__.py
metapathways2/config/__init__.py
metapathways2/executables/__init__.py
metapathways2/executables/linux/__init__.py
metapathways2/executables/linux/bit32/__init__.py
metapathways2/libs/__init__.py
metapathways2/libs/python_modules/__init__.py
metapathways2/libs/python_modules/_metapathways.py
metapathways2/libs/python_modules/annotate/__init__.py
metapathways2/libs/python_modules/annotate/sequence/__init__.py
metapathways2/libs/python_modules/annotate/sequence/fasta.py
metapathways2/libs/python_modules/annotate/sequence/genbank.py
metapathways2/libs/python_modules/annotate/sequence/location.py
metapathways2/libs/python_modules/annotate/sequence/pathologic.py
metapathways2/libs/python_modules/diagnostics/__init__.py
metapathways2/libs/python_modules/diagnostics/configuration.py
metapathways2/libs/python_modules/diagnostics/diagnoze.py
metapathways2/libs/python_modules/diagnostics/parameters.py
metapathways2/libs/python_modules/diagnostics/tools.py
metapathways2/libs/python_modules/grid/BlastBroker.py
metapathways2/libs/python_modules/grid/BlastGrid.py
metapathways2/libs/python_modules/grid/BlastService.py
metapathways2/libs/python_modules/grid/GridParam.py
metapathways2/libs/python_modules/grid/__init__.py
metapathways2/libs/python_modules/grid/blast_using_grid.py
metapathways2/libs/python_modules/parsers/__init__.py
metapathways2/libs/python_modules/parsers/blast.py
metapathways2/libs/python_modules/parsers/fastareader.py
metapathways2/libs/python_modules/parsers/genbank.py
metapathways2/libs/python_modules/parsers/interpro.py
metapathways2/libs/python_modules/parsers/parse.py
metapathways2/libs/python_modules/pipeline/MetaPathways_gather_run_stats.py
metapathways2/libs/python_modules/pipeline/__init__.py
metapathways2/libs/python_modules/pipeline/commands.py
metapathways2/libs/python_modules/pipeline/context.py
metapathways2/libs/python_modules/pipeline/jobscreator.py
