Metadata-Version: 1.0
Name: MetaPathways-Python
Version: v2.1
Summary: A pipeline for MetaGenomic analysis which is capable of creating ePGDBs using Pathway Tools
Home-page: http://packages.python.org/metapathwaysv2
Author: Niels Hanson, Kishori Konwar
Author-email: kishori82@gmail.com
License: BSD
Keywords: metagenomics metapathways pathwaytools epgdb pgdb
Platform: UNKNOWN
